{"id":"e1d0ffb7762a49f3936edc85eaf5099f","name":"P02_获取数据","displayName":"","version":"4.2.0.0","description":"","developType":"visual","parameters":{"input":[],"output":[]},"content":{"id":"canvas-doc-_mpy3pb9t","props":{},"root":{"id":"canvas-node-_mpy3pb9u","type":"FlowRoot","props":{"collapsed":false,"disabled":false,"flowModel":{},"processName":"P02_获取数据"},"children":[{"id":"canvas-node-_mpy3pb9v","type":"StartEvent","props":{"debug":false,"collapsed":false,"disabled":false}},{"id":"canvas-node-_mpy3pbb6","type":"ecgetsheetrowvalue","props":{"rowindex":{"type":"variable","inputValue":"135dd8c430424daeb52bc6bf8db1d342","varLabel":"i","returnType":"Number","varGroup":"global"},"maxcellnumber":{"type":"number","inputValue":1000,"returnType":"Unknown"},"readonlyvisible":"True","gs_pre_timeout":{"type":"number","inputValue":0,"returnType":"Unknown"},"gs_lat_timeout":{"type":"number","inputValue":0,"returnType":"Unknown"},"generalSettings":{"log":{"value":true,"disabled":true},"exit":true,"msgbox":false},"name":"获取Excel行的值","desc":"获取 <a>wyfk_sheet</a> Sheet页的 <a>i</a> 行的值，并将结果赋值给 <a>data</a>","output_valuelist":{"type":"variable","inputValue":"e400aa257bac4d2aaa212bf181f56344","varLabel":"data","returnType":"List","varGroup":"global"},"sheetpage":{"type":"variable","inputValue":"b5edbebbd91444f89f81ab9bfd9ef905","varLabel":"wyfk_sheet","returnType":"Sheet","varGroup":"global"},"collapsed":false,"disabled":false}},{"id":"canvas-node-_mpy3pb9w","type":"EndEvent","props":{"collapsed":false,"disabled":false}}]},"edges":[]}}